aiomemoizeconcurrent.py
aiomemoizeconcurrent-0.0.8.dist-info/LICENSE
aiomemoizeconcurrent-0.0.8.dist-info/METADATA
aiomemoizeconcurrent-0.0.8.dist-info/WHEEL
aiomemoizeconcurrent-0.0.8.dist-info/top_level.txt
aiomemoizeconcurrent-0.0.8.dist-info/RECORD
