Metadata-Version: 2.1
Name: aiomemoizeconcurrent
Version: 0.0.8
Summary: Memoize concurrent asyncio Python function calls
Home-page: https://github.com/michalc/aiomemoizeconcurrent
Author: Michal Charemza
Author-email: michal@charemza.name
License: UNKNOWN
Platform: UNKNOWN
Classifier: Programming Language :: Python :: 3
Classifier: License :: OSI Approved :: MIT License
Classifier: Operating System :: OS Independent
Classifier: Framework :: AsyncIO
Requires-Python: ~=3.5
